setup.cfg
setup.py
kafka_connector/__init__.py
kafka_connector/avro_loop_consumer.py
kafka_connector/avro_loop_producer.py
kafka_connector/timer.py
kafka_connector.egg-info/PKG-INFO
kafka_connector.egg-info/SOURCES.txt
kafka_connector.egg-info/dependency_links.txt
kafka_connector.egg-info/requires.txt
kafka_connector.egg-info/top_level.txt