Metadata-Version: 1.1
Name: kafka-connector
Version: 0.0.4
Summary: A python module for communication with Kafka.
Home-page: https://github.com/smueller18/kafka-connector
Author: Stephan Müller
Author-email: mail@stephanmueller.eu
License: MIT
Download-URL: https://github.com/smueller18/kafka-connector
Platform: UNKNOWN
Classifier: Development Status :: 3 - Alpha
Classifier: Programming Language :: Python :: 2.7
Classifier: Programming Language :: Python :: 3.5
Classifier: License :: OSI Approved :: MIT License
